ai_code_tracker/__init__.py
ai_code_tracker/chart_generator.py
ai_code_tracker/cli.py
ai_code_tracker/contribution_tracker.py
ai_code_tracker/models.py
ai_code_tracker/py.typed
ai_code_tracker-0.1.4.dist-info/METADATA
ai_code_tracker-0.1.4.dist-info/WHEEL
ai_code_tracker-0.1.4.dist-info/entry_points.txt
ai_code_tracker-0.1.4.dist-info/licenses/LICENSE
ai_code_tracker-0.1.4.dist-info/RECORD
