Metadata-Version: 2.4
Name: ai-code-tracker
Version: 0.1.4
Summary: Track and analyze the proportion of AI-assisted vs. human-written code in your Git repositories
Author-email: mrmattwright <matt@sudden.co.nz>
License-File: LICENSE
Requires-Python: >=3.11.8
Requires-Dist: loguru>=0.7.3
Requires-Dist: pandas>=2.2.3
Requires-Dist: plotly>=6.0.0
Requires-Dist: pydantic>=2.10.6
Requires-Dist: pytest>=8.3.4
Requires-Dist: pyyaml>=6.0.2
Requires-Dist: rich>=13.9.4
Requires-Dist: semver>=3.0.4
Requires-Dist: tqdm>=4.67.1
Requires-Dist: typer>=0.15.1
